[
  {
    "intitule": "Identifier les commandes d'installation",
    "type": "ressource",
    "niveau": "easy",
    "enonce": {
      "texte": "<p>Dans un projet React créé avec Vite, vous devez installer et configurer TailwindCSS.</p><p>Listez les commandes npm nécessaires pour installer TailwindCSS et ses dépendances.</p>",
      "images": []
    },
    "questions": [
      {
        "numero": 1,
        "texte": "Énumérer les commandes d'installation de TailwindCSS avec Vite.",
        "niveau": "easy",
        "reponse": "```bash\nnpm install -D tailwindcss postcss autoprefixer\nnpx tailwindcss init -p\n```\nLa première commande installe TailwindCSS, PostCSS et Autoprefixer. La seconde génère les fichiers `tailwind.config.js` et `postcss.config.js`.",
        "sousQuestions": []
      }
    ]
  },
  {
    "intitule": "Configurer les fichiers d'entrée CSS",
    "type": "ressource",
    "niveau": "easy",
    "enonce": {
      "texte": "<p>Après l'installation de TailwindCSS, vous devez configurer le fichier CSS principal pour importer les directives de Tailwind.</p>",
      "images": []
    },
    "questions": [
      {
        "numero": 1,
        "texte": "Écrire le contenu du fichier `src/index.css` ou `src/App.css` pour intégrer Tailwind.",
        "niveau": "easy",
        "reponse": "```css\n@tailwind base;\n@tailwind components;\n@tailwind utilities;\n```\nCes trois directives injectent respectivement le reset de base (Normalize-like), les styles des composants (si définis), et les classes utilitaires de Tailwind.",
        "sousQuestions": []
      }
    ]
  },
  {
    "intitule": "Personnaliser la palette de couleurs",
    "type": "ressource",
    "niveau": "medium",
    "enonce": {
      "texte": "<p>Pour un site e-commerce camerounais, on souhaite utiliser des couleurs personnalisées :</p><ul><li>Primaire : vert (#10B981) - emerald</li><li>Secondaire : orange (#F97316) - orange</li><li>Fond clair : #F9FAFB</li><li>Texte principal : #1F2937</li></ul>",
      "images": []
    },
    "questions": [
      {
        "numero": 1,
        "texte": "Écrire la configuration du fichier `tailwind.config.js` pour étendre ces couleurs personnalisées.",
        "niveau": "medium",
        "reponse": "```javascript\n/** @type {import('tailwindcss').Config} */\nexport default {\n  content: ['./index.html', './src/**/*.{js,ts,jsx,tsx}'],\n  theme: {\n    extend: {\n      colors: {\n        'primary': '#10B981',\n        'secondary': '#F97316',\n        'background': '#F9FAFB',\n        'text-main': '#1F2937',\n      },\n    },\n  },\n  plugins: [],\n}\n```\nOn utilise `extend` pour ajouter des couleurs sans écraser la palette par défaut.",
        "sousQuestions": []
      }
    ]
  },
  {
    "intitule": "Ajouter une police personnalisée",
    "type": "ressource",
    "niveau": "medium",
    "enonce": {
      "texte": "<p>Vous souhaitez utiliser la police <strong>Poppins</strong> de Google Fonts comme police par défaut de l'application.</p><p>La police doit être chargée via Google Fonts puis configurée dans Tailwind.</p>",
      "images": []
    },
    "questions": [
      {
        "numero": 1,
        "texte": "Décrire les étapes pour intégrer Poppins dans l'application (index.html + tailwind.config.js).",
        "niveau": "medium",
        "reponse": "**1. Charger la police dans index.html :**\n```html\n<link href=\"https://fonts.googleapis.com/css2?family=Poppins:wght@300;400;500;600;700&display=swap\" rel=\"stylesheet\">\n```\n\n**2. Configurer Tailwind :**\n```javascript\n// tailwind.config.js\nexport default {\n  theme: {\n    extend: {\n      fontFamily: {\n        'sans': ['Poppins', 'sans-serif'],\n      },\n    },\n  },\n}\n```\nCela remplace la police sans-serif par défaut par Poppins.",
        "sousQuestions": []
      }
    ]
  },
  {
    "intitule": "Personnaliser les breakpoints responsive",
    "type": "ressource",
    "niveau": "hard",
    "enonce": {
      "texte": "<p>Par défaut, Tailwind utilise les breakpoints : sm (640px), md (768px), lg (1024px), xl (1280px), 2xl (1536px).</p><p>Vous devez personnaliser ces points d'arrêt pour coller aux standards de votre projet : mobile-first avec des écrans camerounais majoritairement 360px-420px.</p>",
      "images": []
    },
    "questions": [
      {
        "numero": 1,
        "texte": "Redéfinir les breakpoints dans tailwind.config.js.",
        "niveau": "hard",
        "reponse": "```javascript\nexport default {\n  theme: {\n    screens: {\n      'xs': '375px',     // petits mobiles\n      'sm': '480px',     // mobiles larges\n      'md': '768px',     // tablettes\n      'lg': '1024px',    // petits écrans desktop\n      'xl': '1280px',    // desktop standard\n      '2xl': '1440px',   // grands écrans\n    },\n  },\n}\n```\nAttention : remplacer `screens` (sans `extend`) redéfinit complètement les breakpoints. Si on veut conserver ceux par défaut, on utilise `extend.screens`.",
        "sousQuestions": []
      }
    ]
  },
  {
    "intitule": "Installer et configurer le plugin forms",
    "type": "ressource",
    "niveau": "medium",
    "enonce": {
      "texte": "<p>Le plugin <code>@tailwindcss/forms</code> améliore le style par défaut des champs de formulaire (input, select, checkbox, radio).</p><p>Installez le plugin et configurez-le pour qu'il applique un style global à tous les champs.</p>",
      "images": []
    },
    "questions": [
      {
        "numero": 1,
        "texte": "Écrire les étapes d'installation et de configuration du plugin forms.",
        "niveau": "medium",
        "reponse": "**Installation :**\n```bash\nnpm install -D @tailwindcss/forms\n```\n\n**Configuration dans tailwind.config.js :**\n```javascript\nexport default {\n  content: ['./index.html', './src/**/*.{js,ts,jsx,tsx}'],\n  theme: { extend: {} },\n  plugins: [\n    require('@tailwindcss/forms'),\n  ],\n}\n```\n\n**Options (optionnel) :**\n```javascript\nplugins: [\n  require('@tailwindcss/forms')({\n    strategy: 'base', // ou 'class' pour n'appliquer que si la classe 'form' est présente\n  }),\n],\n```\nPar défaut, le plugin ajoute un reset propre à tous les champs de formulaire.",
        "sousQuestions": []
      }
    ]
  },
  {
    "intitule": "Installer le plugin typography",
    "type": "ressource",
    "niveau": "easy",
    "enonce": {
      "texte": "<p>Le plugin <code>@tailwindcss/typography</code> permet de styliser facilement le contenu HTML riche (articles, descriptions de produits).</p>",
      "images": []
    },
    "questions": [
      {
        "numero": 1,
        "texte": "Expliquer l'utilité du plugin typography et son utilisation dans une page React.",
        "niveau": "easy",
        "reponse": "**Utilité** : Applique des styles typographiques cohérents (titres, paragraphes, listes, citations) à du contenu HTML provenant d'une source externe (ex: description de produit depuis l'API).\n\n**Installation :**\n```bash\nnpm install -D @tailwindcss/typography\n```\n\n**Configuration :**\n```javascript\n// tailwind.config.js\nplugins: [require('@tailwindcss/typography')]\n```\n\n**Utilisation dans un composant :**\n```jsx\n<div \n  className=\"prose prose-lg prose-indigo max-w-none\"\n  dangerouslySetInnerHTML={{ __html: product.description }}\n/>\n```\nLes classes `prose` activent le plugin, `prose-lg` augmente la taille, `prose-indigo` personnalise la couleur des liens.",
        "sousQuestions": []
      }
    ]
  },
  {
    "intitule": "Créer un thème dark mode personnalisé",
    "type": "competence",
    "niveau": "hard",
    "enonce": {
      "texte": "<p>Vous devez configurer le dark mode dans Tailwind avec la stratégie <code>class</code> (pas avec <code>prefers-color-scheme</code>).</p><p>Un bouton doit permettre de basculer entre mode clair et mode sombre.</p>",
      "images": []
    },
    "questions": [
      {
        "numero": 1,
        "texte": "Configurer tailwind.config.js pour le dark mode par classe, puis créer les styles sombres pour un composant.",
        "niveau": "hard",
        "reponse": "**1. Configuration :**\n```javascript\n// tailwind.config.js\nexport default {\n  darkMode: 'class',  // ou 'media' pour auto\n  theme: { extend: {} },\n}\n```\n\n**2. Styles sombres :**\n```jsx\n<div className=\"bg-white dark:bg-gray-900 text-gray-900 dark:text-gray-100\">\n  <h1 className=\"text-2xl font-bold\">Titre</h1>\n  <p className=\"text-gray-600 dark:text-gray-400\">Sous-texte</p>\n  <button className=\"bg-amber-500 dark:bg-amber-700\">Bouton</button>\n</div>\n```\n\n**3. Bascule (avec Zustand ou useState) :**\n```jsx\nconst [darkMode, setDarkMode] = useState(false);\n\nuseEffect(() => {\n  if (darkMode) {\n    document.documentElement.classList.add('dark');\n  } else {\n    document.documentElement.classList.remove('dark');\n  }\n}, [darkMode]);\n```\nLe dark mode s'applique à toute classe préfixée par `dark:`.",
        "sousQuestions": []
      }
    ]
  },
  {
    "intitule": "Optimiser le build de production",
    "type": "competence",
    "niveau": "medium",
    "enonce": {
      "texte": "<p>TailwindCSS génère des centaines de classes utilitaires. En production, seules les classes réellement utilisées doivent être incluses dans le bundle final.</p>",
      "images": []
    },
    "questions": [
      {
        "numero": 1,
        "texte": "Expliquer comment Tailwind supprime les classes inutilisées en production et comment vérifier le contenu analysé.",
        "niveau": "medium",
        "reponse": "Tailwind utilise la configuration `content` pour analyser tous les fichiers et détecter les classes utilisées. Toute classe non détectée est exclue du CSS final.\n\n```javascript\nexport default {\n  content: [\n    './index.html',\n    './src/**/*.{js,ts,jsx,tsx}',\n    './src/**/*.mdx',\n  ],\n}\n```\n\n**Vérification :**\n```bash\nnpm run build\n# Regarder la taille du fichier CSS dans dist/assets/\n```\n\n**Attention** : Les classes construites dynamiquement (ex: `text-${size}`) ne sont pas détectées. Il faut les écrire en toutes lettres ou utiliser la technique des `safelist` :\n```javascript\nsafelist: [\n  'text-red-500',\n  'bg-blue-500',\n  { pattern: /^grid-cols-/ },\n]\n```",
        "sousQuestions": []
      }
    ]
  },
  {
    "intitule": "Calculer des espacements proportionnels",
    "type": "competence",
    "niveau": "medium",
    "enonce": {
      "texte": "<p>Dans un design responsive, les marges doivent être proportionnelles. Tailwind utilise un système d'échelle par défaut (espacement basé sur 0.25rem = 4px).</p><p>Si la taille de base de la police est 16px, calculez la valeur en pixels des classes : <code>p-2</code>, <code>m-4</code>, <code>gap-6</code>.</p><p>Formule : <span class=\"math inline\">$valeur\\ (px) = N \\times 0.25 \\times 16 = N \\times 4$</span></p>",
      "images": []
    },
    "questions": [
      {
        "numero": 1,
        "texte": "Calculer les valeurs en pixels correspondantes.",
        "niveau": "medium",
        "reponse": "- `p-2` : $2 \\times 4 = 8$ pixels\n- `m-4` : $4 \\times 4 = 16$ pixels\n- `gap-6` : $6 \\times 4 = 24$ pixels\n\nL'échelle par défaut suit cette progression arithmétique. On peut étendre cette échelle dans `tailwind.config.js` via `theme.extend.spacing`.",
        "sousQuestions": []
      }
    ]
  }
]