[
  {
    "id": "1",
    "nom": "Les conséquences des Mutilations Génitales Féminines sur la ...",
    "youtubeUrl": "https://www.youtube.com/watch?v=KtgF5uzUSFQ"
  },
  {
    "id": "2",
    "nom": "Carnet de Santé: les mutilations génitales féminines",
    "youtubeUrl": "https://www.youtube.com/watch?v=fZ2zzMxe3XU"
  },
  {
    "id": "3",
    "nom": "Table ronde sur les représentations des femmes et des ...",
    "youtubeUrl": "https://videos.senat.fr/video.2913944_629544fcc0945.table-ronde-sur-les-representations-des-femmes-et-des-sexualites-vehiculees-par-la-pornographie"
  }
]