[
  {
    "intitule": "Calcul de remise avec opérateurs arithmétiques et ternaire",
    "type": "competence",
    "niveau": "medium",
    "enonce": {
      "texte": "<p>Dans une boutique de Douala, un client achète plusieurs articles. Le montant total avant remise est de $45000$ FCFA. Une remise de $10\\%$ est appliquée si le montant dépasse $30000$ FCFA. Écrire un programme C# qui calcule et affiche le montant final à payer.</p>",
      "images": [
        "client dans une boutique avec des billets de francs CFA"
      ]
    },
    "questions": [
      {
        "numero": 1,
        "texte": "Déclarer une variable `montantAvantRemise` de type `double` initialisée à 45000. Appliquer la condition de remise à l'aide de l'opérateur ternaire, puis afficher `montantFinal` avec `Console.WriteLine`.",
        "niveau": "medium",
        "reponse": "```csharp\ndouble montantAvantRemise = 45000;\ndouble montantFinal = montantAvantRemise > 30000 ? montantAvantRemise * 0.9 : montantAvantRemise;\nConsole.WriteLine($\"Montant final : {montantFinal} FCFA\");\n```",
        "sousQuestions": []
      }
    ]
  },
  {
    "intitule": "Vérification d'éligibilité à un prêt bancaire",
    "type": "competence",
    "niveau": "hard",
    "enonce": {
      "texte": "<p>Une banque camerounaise accorde un prêt si :<br> - le revenu mensuel est ≥ 150000 FCFA <strong>et</strong><br> - le nombre d'années d'expérience professionnelle est ≥ 2 <strong>ou</strong><br> - le demandeur a déjà un compte chez eux (booléen `aCompteChezNous`).</p>",
      "images": [
        "personne remplissant un formulaire de prêt dans une banque au Cameroun"
      ]
    },
    "questions": [
      {
        "numero": 1,
        "texte": "Écrire une expression booléenne utilisant les opérateurs logiques (`&&`, `||`) pour déterminer l'éligibilité à partir des variables : `revenuMensuel`, `experience`, `aCompteChezNous`. Tester avec : revenu = 200000 FCFA, experience = 1 an, aCompteChezNous = false.",
        "niveau": "hard",
        "reponse": "```csharp\nbool eligible = (revenuMensuel >= 150000 && experience >= 2) || aCompteChezNous;\n// Avec les valeurs : (200000 >= 150000 && 1 >= 2) || false → (true && false) || false → false || false → false\n```",
        "sousQuestions": [
          {
            "numero": "1.a",
            "texte": "Analyser pourquoi le client n'est pas éligible malgré un bon revenu. Proposer une modification de l'expression logique pour qu'un revenu ≥ 150000 suffise si la personne a au moins un an d'expérience.",
            "niveau": "medium",
            "reponse": "Le client n'est pas éligible car `experience` (1) n'est pas ≥ 2. Pour rendre éligible avec 1 an d'expérience : `(revenuMensuel >= 150000 && experience >= 1) || aCompteChezNous`."
          }
        ]
      }
    ]
  },
  {
    "intitule": "QCM : Opérateurs de base en C#",
    "type": "ressource",
    "niveau": "easy",
    "enonce": {
      "texte": "<p>Cocher la ou les bonnes réponses pour chaque question.</p>",
      "images": []
    },
    "questions": [
      {
        "numero": 1,
        "texte": "Que vaut `result` après `int result = 15 % 4;` ?",
        "niveau": "easy",
        "reponse": "3",
        "sousQuestions": []
      },
      {
        "numero": 2,
        "texte": "Quel est le résultat de l’expression `(8 > 5) && (3 < 1)` ?",
        "niveau": "easy",
        "reponse": "false",
        "sousQuestions": []
      },
      {
        "numero": 3,
        "texte": "Expliquer la différence entre `=` et `==` en C#.",
        "niveau": "medium",
        "reponse": "`=` est l'opérateur d'affectation (assignation d'une valeur à une variable). `==` est l'opérateur de comparaison d'égalité (retourne true ou false).",
        "sousQuestions": []
      }
    ]
  },
  {
    "intitule": "Simulation d'un compteur de tasses de café",
    "type": "competence",
    "niveau": "easy",
    "enonce": {
      "texte": "<p>Un développeur veut compter combien de tasses de café il boit par jour. Il commence à 0, boit 3 tasses le matin, puis 2 l'après-midi. Utiliser l'opérateur `++` pour incrémenter.</p>",
      "images": [
        "tasse de café à côté d'un ordinateur portable"
      ]
    },
    "questions": [
      {
        "numero": 1,
        "texte": "Écrire un programme C# qui déclare `int tasses = 0;` et simule l’ajout des 3 tasses du matin (incrémentations séparées), puis 2 tasses de l’après-midi. Afficher le total.",
        "niveau": "easy",
        "reponse": "```csharp\nint tasses = 0;\ntasses++; // tasse 1\ntasses++; // tasse 2\ntasses++; // tasse 3 (matin)\ntasses++; // après-midi 1\ntasses++; // après-midi 2\nConsole.WriteLine($\"Total de tasses : {tasses}\"); // 5\n```",
        "sousQuestions": []
      }
    ]
  },
  {
    "intitule": "Calcul du périmètre d’un champ agricole",
    "type": "ressource",
    "niveau": "medium",
    "enonce": {
      "texte": "<p>Un agriculteur à Yaoundé a un champ rectangulaire de longueur $L = 120\\,m$ et largeur $l = 80\\,m$. Il souhaite automatiser le calcul du périmètre $P = 2 \\times (L + l)$.</p>",
      "images": [
        "champ rectangulaire de maïs ou de manioc au Cameroun"
      ]
    },
    "questions": [
      {
        "numero": 1,
        "texte": "Développer un programme C# avec des variables `double longueur` et `double largeur`. Calculer le périmètre en respectant les priorités des opérateurs, puis l'afficher.",
        "niveau": "medium",
        "reponse": "```csharp\ndouble longueur = 120;\ndouble largeur = 80;\ndouble perimetre = 2 * (longueur + largeur);\nConsole.WriteLine($\"Périmètre : {perimetre} m\"); // 400 m\n```",
        "sousQuestions": [
          {
            "numero": "1.a",
            "texte": "Modifier le calcul en utilisant l’opérateur d’affectation composée pour multiplier `perimetre` par 1.1 (ajout d’une clôture supplémentaire de 10%).",
            "niveau": "medium",
            "reponse": "`perimetre *= 1.1;`"
          }
        ]
      }
    ]
  }
]