[
  {
    "intitule": "Détermination du Ka et du pKa d'un acide faible (Exercice ressource)",
    "type": "ressource",
    "niveau": "medium",
    "enonce": {
      "texte": "<p>On prépare une solution aqueuse d'acide éthanoïque (CH<sub>3</sub>COOH) de concentration molaire apportée C = 1,0 × 10<sup>-2</sup> mol·L<sup>-1</sup>. À 25°C, on mesure le pH de cette solution et on trouve pH = 3,4.</p><p>Donnée : À 25°C, $K_e = 1,0 \\times 10^{-14}$.</p>",
      "images": []
    },
    "questions": [
      {
        "numero": 1,
        "texte": "Expliquer pourquoi l'acide éthanoïque est un acide faible.",
        "niveau": "easy",
        "reponse": "L'acide éthanoïque est un acide faible car sa réaction avec l'eau n'est pas totale. Il existe un équilibre chimique entre l'acide et sa base conjuguée, ce qui explique que le pH de sa solution soit supérieur à celui d'un acide fort de même concentration (qui serait pH = -log(0.01) = 2).",
        "sousQuestions": []
      },
      {
        "numero": 2,
        "texte": "Calculer la concentration en ions oxonium $[\\text{H}_3\\text{O}^+]$ à l'équilibre.",
        "niveau": "easy",
        "reponse": "$[\\text{H}_3\\text{O}^+] = 10^{-\\text{pH}} = 10^{-3.4} = 4,0 \\times 10^{-4} \\text{ mol·L}^{-1}$.",
        "sousQuestions": []
      },
      {
        "numero": 3,
        "texte": "Dresser le tableau d'avancement (ou tableau de réaction) de la réaction de l'acide éthanoïque avec l'eau, puis déterminer les concentrations à l'équilibre de toutes les espèces chimiques (CH<sub>3</sub>COOH, CH<sub>3</sub>COO<sup>-</sup> et H<sub>3</sub>O<sup>+</sup>).",
        "niveau": "medium",
        "reponse": "<p>Réaction : CH<sub>3</sub>COOH + H<sub>2</sub>O ⇌ CH<sub>3</sub>COO<sup>-</sup> + H<sub>3</sub>O<sup>+</sup></p><p>Tableau d'avancement (volume V = 1L) :</p><ul><li>État initial : $n_{acide}=C$, $n_{base}=0$, $n_{oxonium}=0$.</li><li>État intermédiaire : $n_{acide}=C-x$, $n_{base}=x$, $n_{oxonium}=x$.</li><li>État final : $n_{acide}=C-x_f$, $n_{base}=x_f$, $n_{oxonium}=x_f$.</li></ul><p>Avec $x_f = [\\text{H}_3\\text{O}^+] = 4,0 \\times 10^{-4}$ mol.</p><p>Concentrations à l'équilibre :</p><ul><li>$[\\text{CH}_3\\text{COOH}] = C - x_f = 1,0\\times10^{-2} - 4,0\\times10^{-4} = 9,6 \\times 10^{-3} \\text{ mol·L}^{-1}$</li><li>$[\\text{CH}_3\\text{COO}^-] = x_f = 4,0 \\times 10^{-4} \\text{ mol·L}^{-1}$</li><li>$[\\text{H}_3\\text{O}^+] = 4,0 \\times 10^{-4} \\text{ mol·L}^{-1}$</li></ul>",
        "sousQuestions": []
      },
      {
        "numero": 4,
        "texte": "Écrire l'expression de la constante d'acidité $K_a$ du couple CH<sub>3</sub>COOH / CH<sub>3</sub>COO<sup>-</sup>.",
        "niveau": "easy",
        "reponse": "$K_a = \\dfrac{[\\text{CH}_3\\text{COO}^-] \\times [\\text{H}_3\\text{O}^+]}{[\\text{CH}_3\\text{COOH}]}$",
        "sousQuestions": []
      },
      {
        "numero": 5,
        "texte": "Calculer la valeur de $K_a$ puis celle de $pK_a$ pour le couple de l'acide éthanoïque.",
        "niveau": "medium",
        "reponse": "$K_a = \\dfrac{(4,0 \\times 10^{-4}) \\times (4,0 \\times 10^{-4})}{9,6 \\times 10^{-3}} = \\dfrac{1,6 \\times 10^{-7}}{9,6 \\times 10^{-3}} = 1,7 \\times 10^{-5}$<br>$pK_a = -\\log(K_a) = -\\log(1,7 \\times 10^{-5}) = 4,8$",
        "sousQuestions": []
      }
    ]
  },
  {
    "intitule": "Choix d'un indicateur coloré pour le dosage d'un acide faible (Exercice compétence)",
    "type": "competence",
    "niveau": "hard",
    "enonce": {
      "texte": "<p>Dans un laboratoire de contrôle qualité, un technicien doit doser une solution d'acide lactique (CH<sub>3</sub>-CHOH-COOH) présent dans un échantillon de yaourt. L'acide lactique est un acide faible dont le $pK_a$ est de 3,9 à 25°C. La solution à doser a une concentration $C_a$ inconnue. Le technicien dispose d'une solution d'hydroxyde de sodium (NaOH) de concentration $C_b = 1,0 \\times 10^{-1}$ mol·L<sup>-1</sup> et de plusieurs indicateurs colorés.</p><p>Données :</p><ul><li>Bleu de bromothymol (BBT) : zone de virage pH = 6,0 – 7,6</li><li>Phénolphtaléine : zone de virage pH = 8,2 – 10,0</li><li>Hélianthine : zone de virage pH = 3,1 – 4,4</li></ul>",
      "images": []
    },
    "questions": [
      {
        "numero": 1,
        "texte": "Rappeler la relation qui lie le pH, le $pK_a$ et les concentrations de l'acide et de sa base conjuguée pour un acide faible.",
        "niveau": "easy",
        "reponse": "La relation est $\\text{pH} = pK_a + \\log\\left(\\dfrac{[\\text{base conjuguée}]}{[\\text{acide}]}\\right)$. C'est l'équation de Henderson-Hasselbalch.",
        "sousQuestions": []
      },
      {
        "numero": 2,
        "texte": "Au point de demi-équivalence d'un dosage acide faible - base forte, démontrer pourquoi le pH est égal au $pK_a$ du couple de l'acide faible.",
        "niveau": "medium",
        "reponse": "Au point de demi-équivalence, la moitié de l'acide faible initial a été neutralisé par la base forte. Il reste donc une quantité d'acide égale à la quantité de base conjuguée formée, soit $[\\text{acide}] = [\\text{base conjuguée}]$. En appliquant la relation $\\text{pH} = pK_a + \\log\\left(\\dfrac{[\\text{base}]}{[\\text{acide}]}\\right)$, on obtient $\\text{pH} = pK_a + \\log(1) = pK_a$.",
        "sousQuestions": []
      },
      {
        "numero": 3,
        "texte": "Déterminer le pH théorique au point d'équivalence du dosage de l'acide lactique par la soude. Justifier pourquoi ce pH n'est pas égal à 7.",
        "niveau": "hard",
        "reponse": "Au point d'équivalence, tout l'acide lactique a été transformé en sa base conjuguée, l'ion lactate (CH<sub>3</sub>-CHOH-COO<sup>-</sup>). L'ion lactate est une base faible (car c'est la base conjuguée d'un acide faible). Il réagit avec l'eau selon la réaction : $\\text{CH}_3\\text{-CHOH-COO}^- + \\text{H}_2\\text{O} \\rightleftharpoons \\text{CH}_3\\text{-CHOH-COOH} + \\text{OH}^-$. La solution est donc basique, avec un pH > 7. Pour calculer exactement le pH, il faudrait la concentration, mais il sera typiquement entre 8 et 9.",
        "sousQuestions": []
      },
      {
        "numero": 4,
        "texte": "Parmi les trois indicateurs proposés, lequel est le plus adapté pour repérer visuellement l'équivalence de ce dosage ? Justifier votre réponse.",
        "niveau": "medium",
        "reponse": "Le pH au point d'équivalence étant basique (environ 8-9), la zone de virage de l'indicateur doit inclure cette valeur. Le BBT vire entre 6,0 et 7,6 (zone plutôt neutre), l'hélianthine vire en milieu acide (3,1-4,4). La phénolphtaléine vire entre 8,2 et 10,0, ce qui correspond parfaitement au pH basique attendu à l'équivalence. L'indicateur le plus adapté est donc la **phénolphtaléine**.",
        "sousQuestions": []
      },
      {
        "numero": 5,
        "texte": "Lors du dosage, le technicien obtient un volume à l'équivalence $V_{bE} = 12,5 \\text{ mL}$ pour un volume initial d'acide lactique $V_a = 20,0 \\text{ mL}$. Calculer la concentration molaire $C_a$ de l'acide lactique dans le yaourt.",
        "niveau": "medium",
        "reponse": "À l'équivalence d'un dosage acide-base, les quantités de matière de réactifs introduits sont stœchiométriques. La réaction étant 1:1 (un acide réagit avec une base), on a : $C_a \\times V_a = C_b \\times V_{bE}$.<br>Donc $C_a = \\dfrac{C_b \\times V_{bE}}{V_a} = \\dfrac{1,0 \\times 10^{-1} \\times 12,5}{20,0} = \\dfrac{1,25}{20,0} = 6,25 \\times 10^{-2} \\text{ mol·L}^{-1}$.",
        "sousQuestions": []
      }
    ]
  },
  {
    "intitule": "Relation entre pH, pKa et domaines de prédominance (Exercice ressource)",
    "type": "ressource",
    "niveau": "medium",
    "enonce": {
      "texte": "<p>On considère un couple acide-base noté $\\text{AH}/\\text{A}^-$ dont le $pK_a$ est égal à 5,0 à 25°C.</p>",
      "images": []
    },
    "questions": [
      {
        "numero": 1,
        "texte": "Calculer le rapport $\\dfrac{[\\text{A}^-]}{[\\text{AH}]}$ pour un pH = 5,0.",
        "niveau": "easy",
        "reponse": "pH = pKa + log([A-]/[AH]) => 5,0 = 5,0 + log([A-]/[AH]) => log([A-]/[AH]) = 0 => [A-]/[AH] = 1. Les deux espèces sont en concentrations égales.",
        "sousQuestions": []
      },
      {
        "numero": 2,
        "texte": "Déterminer l'espèce chimique prédominante pour un pH = 3,0. Justifier par le calcul.",
        "niveau": "easy",
        "reponse": "pH = 3,0 < pKa (5,0). D'après la relation, log([A-]/[AH]) = pH - pKa = 3,0 - 5,0 = -2,0. Donc [A-]/[AH] = 10^{-2} = 0,01. La concentration de AH est 100 fois supérieure à celle de A-, donc AH prédomine.",
        "sousQuestions": []
      },
      {
        "numero": 3,
        "texte": "Représenter le diagramme de prédominance du couple AH/A- en fonction du pH.",
        "niveau": "medium",
        "reponse": "Le diagramme est un axe gradué en pH. On place une barre verticale à pH = pKa = 5,0. À gauche (pH < 5,0), on écrit 'AH prédomine'. À droite (pH > 5,0), on écrit 'A- prédomine'. Au point pH = 5,0, [AH] = [A-].",
        "sousQuestions": []
      },
      {
        "numero": 4,
        "texte": "À quel pH la forme basique A- est-elle 100 fois plus concentrée que la forme acide AH ?",
        "niveau": "hard",
        "reponse": "On cherche pH tel que [A-]/[AH] = 100. Alors log([A-]/[AH]) = log(100) = 2. Or pH = pKa + log([A-]/[AH]) = 5,0 + 2 = 7,0. À pH = 7,0, la forme basique prédomine largement (100 fois plus que la forme acide).",
        "sousQuestions": []
      }
    ]
  }
]