[
  {
    "intitule": "Vocabulary Check: Periods of the Day",
    "type": "ressource",
    "niveau": "easy",
    "enonce": {
      "texte": "<p><strong>Instructions:</strong> Match the words on the left with their correct definitions on the right. Write the letter of the definition next to the word.</p><ul style='list-style-type: none;'><li><strong>1. Morning</strong> → ...</li><li><strong>2. Afternoon</strong> → ...</li><li><strong>3. Evening</strong> → ...</li><li><strong>4. Night</strong> → ...</li><li><strong>5. Sunrise</strong> → ...</li><li><strong>6. Sunset</strong> → ...</li></ul><p><strong>Definitions:</strong></p><ul style='list-style-type: lower-alpha;'><li>A. The time when the sun goes down in the evening.</li><li>B. The time when the sun comes up in the morning.</li><li>C. The early part of the day, from sunrise to noon.</li><li>D. The part of the day from noon to evening.</li><li>E. The period between sunset and sunrise when it is dark.</li><li>F. The last part of the day, from late afternoon to night.</li></ul>",
      "images": []
    },
    "questions": [
      {
        "numero": 1,
        "texte": "Match each word to its correct definition.",
        "niveau": "easy",
        "reponse": "1-C, 2-D, 3-F, 4-E, 5-B, 6-A",
        "sousQuestions": []
      }
    ]
  },
  {
    "intitule": "Fill in the Blanks: Daily Routines",
    "type": "ressource",
    "niveau": "medium",
    "enonce": {
      "texte": "<p><strong>Instructions:</strong> Complete each sentence with the correct word from the box below.</p><div style='background-color: #f0f4f8; padding: 10px; border-radius: 6px; margin: 10px 0;'><p><strong>Word Box:</strong> <em>morning, afternoon, evening, night, sunrise, sunset</em></p></div><ol><li>I wake up at _______ every day.</li><li>We have lunch in the _______.</li><li>My family watches TV in the _______.</li><li>I go to bed at _______.</li><li>The sky is beautiful at _______.</li><li>We see the sun come up at _______.</li></ol>",
      "images": []
    },
    "questions": [
      {
        "numero": 1,
        "texte": "Fill in each blank with the appropriate word from the box.",
        "niveau": "medium",
        "reponse": "1. sunrise, 2. afternoon, 3. evening, 4. night, 5. sunset, 6. sunrise",
        "sousQuestions": []
      }
    ]
  },
  {
    "intitule": "Identifying Daily Routines",
    "type": "ressource",
    "niveau": "medium",
    "enonce": {
      "texte": "<p><strong>Instructions:</strong> Read each sentence and identify the period of the day (morning, afternoon, evening, night).</p><ol><li>I brush my teeth at 7:00 AM. → ______</li><li>We eat dinner at 7:00 PM. → ______</li><li>She goes to school at 8:00 AM. → ______</li><li>They watch the stars at 9:00 PM. → ______</li><li>We play football at 4:00 PM. → ______</li><li>I do my homework at 6:00 PM. → ______</li></ol>",
      "images": []
    },
    "questions": [
      {
        "numero": 1,
        "texte": "Identify the period of the day for each activity.",
        "niveau": "medium",
        "reponse": "1. morning, 2. evening, 3. morning, 4. night, 5. afternoon, 6. evening",
        "sousQuestions": []
      }
    ]
  },
  {
    "intitule": "Reading Comprehension: Daily Routine",
    "type": "competence",
    "niveau": "medium",
    "enonce": {
      "texte": "<p><strong>Instructions:</strong> Read the text below and answer the questions that follow.</p><div style='background-color: #e8f5e9; padding: 15px; border-radius: 8px; margin: 10px 0;'><p><strong>Text:</strong></p><p>My name is Marie. I am a student in Class 6. Every day, I wake up at 6:00 AM in the morning. I brush my teeth and take a shower. At 7:00 AM, I have breakfast with my family. I go to school at 7:30 AM. In the afternoon, I eat lunch at 12:30 PM with my friends. I come back home at 3:30 PM. In the evening, I do my homework and watch TV. I have dinner at 7:00 PM with my parents. At night, I read a book and go to bed at 9:30 PM.</p></div><ol><li>What time does Marie wake up?</li><li>When does Marie have breakfast?</li><li>What does Marie do in the afternoon?</li><li>What does Marie do in the evening?</li><li>What time does Marie go to bed?</li></ol>",
      "images": []
    },
    "questions": [
      {
        "numero": 1,
        "texte": "Answer the questions based on the text.",
        "niveau": "medium",
        "reponse": "1. She wakes up at 6:00 AM.<br>2. She has breakfast at 7:00 AM.<br>3. She eats lunch and comes back home.<br>4. She does her homework and watches TV.<br>5. She goes to bed at 9:30 PM.",
        "sousQuestions": []
      }
    ]
  },
  {
    "intitule": "Writing: My Daily Routine",
    "type": "competence",
    "niveau": "hard",
    "enonce": {
      "texte": "<p><strong>Instructions:</strong> Write a short paragraph (5-7 sentences) about your daily routine. Include the periods of the day: <em>morning, afternoon, evening, night</em>. Also mention what you do at each period.</p><div style='background-color: #fff3e0; padding: 15px; border-radius: 8px; margin: 10px 0;'><p><strong>Guidelines:</strong></p><ul><li>Start with your wake-up time.</li><li>Describe your activities in the morning, afternoon, evening, and night.</li><li>Use the vocabulary from the lesson.</li></ul></div>",
      "images": []
    },
    "questions": [
      {
        "numero": 1,
        "texte": "Write a paragraph about your daily routine.",
        "niveau": "hard",
        "reponse": "<p><strong>Sample answer:</strong></p><p><em>I wake up at 6:00 AM in the morning. I brush my teeth and take a shower. I have breakfast at 7:00 AM and then go to school. In the afternoon, I eat lunch at 12:30 PM and play with my friends. I come back home at 3:30 PM. In the evening, I do my homework and help my mother. I have dinner at 7:00 PM. At night, I watch a little TV and then go to bed at 9:00 PM.</em></p>",
        "sousQuestions": []
      }
    ]
  },
  {
    "intitule": "True or False: Daily Activities",
    "type": "ressource",
    "niveau": "easy",
    "enonce": {
      "texte": "<p><strong>Instructions:</strong> Read each sentence and write <strong>True</strong> or <strong>False</strong>.</p><ol><li>We eat breakfast in the morning. ______</li><li>We go to bed in the afternoon. ______</li><li>The sun rises in the evening. ______</li><li>We have lunch in the afternoon. ______</li><li>We watch stars at night. ______</li><li>The sun sets in the morning. ______</li></ol>",
      "images": []
    },
    "questions": [
      {
        "numero": 1,
        "texte": "Write True or False for each statement.",
        "niveau": "easy",
        "reponse": "1. True, 2. False, 3. False, 4. True, 5. True, 6. False",
        "sousQuestions": []
      }
    ]
  },
  {
    "intitule": "Rearranging Sentences",
    "type": "competence",
    "niveau": "hard",
    "enonce": {
      "texte": "<p><strong>Instructions:</strong> Rearrange the words to make correct sentences about daily routines.</p><ol><li>I / morning / wake / in / up / the / at / 6:00.</li><li>lunch / afternoon / we / the / in / eat.</li><li>evening / homework / do / the / I / my / in.</li><li>night / to / go / bed / at / I / 9:30.</li><li>morning / breakfast / the / have / in / I.</li></ol>",
      "images": []
    },
    "questions": [
      {
        "numero": 1,
        "texte": "Rearrange the words to form correct sentences.",
        "niveau": "hard",
        "reponse": "1. I wake up at 6:00 in the morning.<br>2. We eat lunch in the afternoon.<br>3. I do my homework in the evening.<br>4. I go to bed at 9:30 at night.<br>5. I have breakfast in the morning.",
        "sousQuestions": []
      }
    ]
  },
  {
    "intitule": "Creating a Daily Schedule",
    "type": "competence",
    "niveau": "very hard",
    "enonce": {
      "texte": "<p><strong>Instructions:</strong> Create a daily schedule for yourself. Write down what you do at different times of the day. Use the periods: <em>morning, afternoon, evening, night</em>.</p><div style='background-color: #e1f5fe; padding: 15px; border-radius: 8px; margin: 10px 0;'><p><strong>Example:</strong></p><table style='width: 100%; border-collapse: collapse;'><tr style='background-color: #bbdefb;'><th style='padding: 8px; border: 1px solid #ddd;'>Time</th><th style='padding: 8px; border: 1px solid #ddd;'>Activity</th></tr><tr><td style='padding: 8px; border: 1px solid #ddd;'>6:00 AM</td><td style='padding: 8px; border: 1px solid #ddd;'>Wake up</td></tr><tr><td style='padding: 8px; border: 1px solid #ddd;'>7:00 AM</td><td style='padding: 8px; border: 1px solid #ddd;'>Have breakfast</td></tr></table></div><p>Your schedule should have at least <strong>6 activities</strong>.</p>",
      "images": []
    },
    "questions": [
      {
        "numero": 1,
        "texte": "Create a daily schedule with at least 6 activities.",
        "niveau": "very hard",
        "reponse": "<p><strong>Sample answer:</strong></p><table style='width: 100%; border-collapse: collapse;'><tr style='background-color: #bbdefb;'><th style='padding: 8px; border: 1px solid #ddd;'>Time</th><th style='padding: 8px; border: 1px solid #ddd;'>Activity</th></tr><tr><td style='padding: 8px; border: 1px solid #ddd;'>6:00 AM</td><td style='padding: 8px; border: 1px solid #ddd;'>Wake up</td></tr><tr><td style='padding: 8px; border: 1px solid #ddd;'>7:00 AM</td><td style='padding: 8px; border: 1px solid #ddd;'>Have breakfast</td></tr><tr><td style='padding: 8px; border: 1px solid #ddd;'>8:00 AM</td><td style='padding: 8px; border: 1px solid #ddd;'>Go to school</td></tr><tr><td style='padding: 8px; border: 1px solid #ddd;'>12:30 PM</td><td style='padding: 8px; border: 1px solid #ddd;'>Eat lunch</td></tr><tr><td style='padding: 8px; border: 1px solid #ddd;'>3:30 PM</td><td style='padding: 8px; border: 1px solid #ddd;'>Come back home</td></tr><tr><td style='padding: 8px; border: 1px solid #ddd;'>7:00 PM</td><td style='padding: 8px; border: 1px solid #ddd;'>Have dinner</td></tr><tr><td style='padding: 8px; border: 1px solid #ddd;'>9:00 PM</td><td style='padding: 8px; border: 1px solid #ddd;'>Go to bed</td></tr></table>",
        "sousQuestions": []
      }
    ]
  }
]