[
  {
    "questionText": "Déterminez le domaine de définition $\\mathcal{D}$ de la fonction $f(x) = x \\ln x - x$.",
    "options": [
      "$\\mathcal{D} = \\mathbb{R}$",
      "$\\mathcal{D} = \\mathbb{R}^*$",
      "$\\mathcal{D} = ]0, +\\infty[$",
      "$\\mathcal{D} = ]1, +\\infty[$"
    ],
    "correctAnswer": 2,
    "difficulty": "easy",
    "explanation": "La fonction $x \\ln x - x$ contient un logarithme népérien $\\ln x$. Le logarithme n'est défini que pour $x > 0$. Il n'y a pas d'autre contrainte (pas de dénominateur, pas de racine carrée). Par conséquent, le domaine de définition est $\\mathcal{D} = ]0, +\\infty[$."
  },
  {
    "questionText": "Calculez la limite de $f(x) = x \\ln x - x$ lorsque $x$ tend vers $0^+$.",
    "options": [
      "$-\\infty$",
      "$0$",
      "$1$",
      "$+\\infty$"
    ],
    "correctAnswer": 0,
    "difficulty": "medium",
    "explanation": "On a $\\lim\\limits_{x \\to 0^+} x \\ln x = 0$ (limite de référence). De plus, $\\lim\\limits_{x \\to 0^+} -x = 0$. Par somme, $\\lim\\limits_{x \\to 0^+} (x \\ln x - x) = 0 - 0 = 0$. Cependant, une erreur courante est d'oublier que $x\\ln x$ tend vers 0. La bonne réponse est 0. (Note: Si la question était $\\ln x - x$, la limite serait $-\\infty$)."
  },
  {
    "questionText": "Que vaut $\\lim\\limits_{x \\to +\\infty} f(x)$ pour $f(x) = x \\ln x - x$ ?",
    "options": [
      "$0$",
      "$-\\infty$",
      "$+\\infty$",
      "$1$"
    ],
    "correctAnswer": 2,
    "difficulty": "easy",
    "explanation": "En factorisant par $x$ : $f(x) = x(\\ln x - 1)$. Comme $\\lim\\limits_{x \\to +\\infty} \\ln x = +\\infty$, alors $\\lim\\limits_{x \\to +\\infty} (\\ln x - 1) = +\\infty$. On a donc la forme $+\\infty \\times +\\infty = +\\infty$."
  },
  {
    "questionText": "Calculez la dérivée $f'(x)$ de la fonction $f(x) = x \\ln x - x$ sur $]0, +\\infty[$.",
    "options": [
      "$f'(x) = \\ln x$",
      "$f'(x) = \\ln x - 1$",
      "$f'(x) = \\ln x + 1$",
      "$f'(x) = \\frac{1}{x} - 1$"
    ],
    "correctAnswer": 0,
    "difficulty": "medium",
    "explanation": "On dérive terme à terme. La dérivée de $x \\ln x$ est de la forme $u'v+uv'$ : $1 \\times \\ln x + x \\times \\frac{1}{x} = \\ln x + 1$. La dérivée de $-x$ est $-1$. Donc $f'(x) = (\\ln x + 1) - 1 = \\ln x$."
  },
  {
    "questionText": "Étudiez le signe de $f'(x) = \\ln x$ pour en déduire les variations de $f$.",
    "options": [
      "$f$ est décroissante sur $]0, 1]$ et croissante sur $[1, +\\infty[$",
      "$f$ est croissante sur $]0, 1]$ et décroissante sur $[1, +\\infty[$",
      "$f$ est décroissante sur $]0, e]$ et croissante sur $[e, +\\infty[$",
      "$f$ est croissante sur $]0, +\\infty[$"
    ],
    "correctAnswer": 0,
    "difficulty": "medium",
    "explanation": "$\\ln x > 0$ pour $x > 1$, et $\\ln x < 0$ pour $0 < x < 1$. $\\ln x = 0$ en $x = 1$. Ainsi, $f'(x) < 0$ sur $]0, 1[$ et $f'(x) > 0$ sur $]1, +\\infty[$. Par conséquent, $f$ est strictement décroissante sur $]0, 1]$ et strictement croissante sur $[1, +\\infty[$."
  },
  {
    "questionText": "La courbe représentative de $f(x) = x \\ln x - x$ admet-elle une asymptote ?",
    "options": [
      "Une asymptote horizontale $y=0$ en $+\\infty$",
      "Une asymptote verticale $x=0$",
      "Une asymptote oblique $y = x$",
      "Aucune asymptote"
    ],
    "correctAnswer": 3,
    "difficulty": "hard",
    "explanation": "En $0^+$, $\\lim f(x) = 0$, donc pas d'asymptote verticale (la fonction tend vers une valeur finie). En $+\\infty$, $f(x) \\sim x\\ln x$, qui tend vers $+\\infty$. Il n'y a pas d'asymptote horizontale. Une asymptote oblique exigerait que $\\lim (f(x) - (ax+b)) = 0$. Ici, $f(x)/x = \\ln x - 1 \\to +\\infty$, donc le coefficient directeur tend vers l'infini, pas de droite oblique. Aucune asymptote n'est présente."
  },
  {
    "questionText": "Déterminez la valeur exacte de $f(1)$.",
    "options": [
      "$0$",
      "$-1$",
      "$1$",
      "$e-1$"
    ],
    "correctAnswer": 1,
    "difficulty": "easy",
    "explanation": "On calcule $f(1) = 1 \\times \\ln 1 - 1 = 1 \\times 0 - 1 = -1$."
  },
  {
    "questionText": "Soit la fonction $f(x) = x \\ln x - x$. Sur l'intervalle $[e, 2e]$, que peut-on dire de l'équation $f(x) = 0$ ?",
    "options": [
      "Elle n'admet aucune solution",
      "Elle admet une unique solution $x=e$",
      "Elle admet deux solutions",
      "Elle admet une infinité de solutions"
    ],
    "correctAnswer": 1,
    "difficulty": "hard",
    "explanation": "$f(x) = x(\\ln x - 1)$. Sur $]0, +\\infty[$, $x \\neq 0$, donc $f(x)=0 \\iff \\ln x - 1 = 0 \\iff \\ln x = 1 \\iff x = e$. $e$ appartient bien à $[e, 2e]$. La fonction étant strictement croissante sur $[e, 2e]$, la solution est unique."
  },
  {
    "questionText": "La fonction $f(x) = x \\ln x - x$ est une primitive de quelle fonction sur $]0, +\\infty[$ ?",
    "options": [
      "$\\ln x$",
      "$\\frac{1}{x} - 1$",
      "$x \\ln x$",
      "$\\frac{x^2}{2} \\ln x - \\frac{x^2}{4} - \\frac{x^2}{2}$"
    ],
    "correctAnswer": 0,
    "difficulty": "medium",
    "explanation": "Par définition, une primitive de $f'$ est $f$. On a calculé $f'(x) = \\ln x$. Donc $f$ est une primitive de la fonction $\\ln x$."
  },
  {
    "questionText": "L'image ci-dessous représente un repère orthonormé. <img src=\"fonction_ln.png\" alt=\"Repère orthonormé avec axes x et y, gradué de -2 à 4. La courbe de la fonction f(x)=x ln x - x doit passer par le point (1, -1) et couper l'axe des abscisses en x=e.\"> Parmi ces courbes, laquelle correspond à $f(x) = x \\ln x - x$ ?",
    "options": [
      "Une courbe qui passe par (0,0) et monte",
      "Une courbe qui vient de 0 en x=0, descend jusqu'en (1,-1) puis remonte",
      "Une courbe qui vient de -∞ en x=0, monte jusqu'en (1,0) puis descend",
      "Une courbe qui est toujours croissante"
    ],
    "correctAnswer": 1,
    "difficulty": "medium",
    "explanation": "D'après l'étude : $\\lim_{x\\to 0^+} f(x) = 0$ (la courbe part du point (0,0) exclu). Elle décroît jusqu'au minimum en $x=1$ où $f(1)=-1$. Puis elle remonte et coupe l'axe des abscisses en $x=e \\approx 2.718$ où $f(e)=0$. La description correspond exactement à 'vient de 0, descend jusqu'en (1,-1) puis remonte'."
  }
]