[
  {
    "intitule": "Incertitude absolue et relative",
    "type": "ressource",
    "niveau": "easy",
    "enonce": {
      "texte": "<p>Un élève mesure la longueur d'une table avec une règle graduée en millimètres. Il obtient $L = 1,234 \\ m$.</p><p>L'incertitude de la mesure est estimée à $\\Delta L = 0,001 \\ m$ (1 mm).</p>",
      "images": []
    },
    "questions": [
      {
        "numero": 1,
        "texte": "Définir l'incertitude absolue et l'incertitude relative.",
        "niveau": "easy",
        "reponse": "<p>L'<strong>incertitude absolue</strong> ($\\Delta x$) est la valeur qui exprime la précision de la mesure. Elle a la même unité que la grandeur mesurée.</p><p>L'<strong>incertitude relative</strong> est le rapport entre l'incertitude absolue et la valeur mesurée : $\\dfrac{\\Delta x}{x}$. Elle est sans unité et souvent exprimée en pourcentage.</p>",
        "sousQuestions": []
      },
      {
        "numero": 2,
        "texte": "Calculer l'incertitude relative de cette mesure.",
        "niveau": "easy",
        "reponse": "<p>$\\dfrac{\\Delta L}{L} = \\dfrac{0,001}{1,234} \\approx 8,10 \\times 10^{-4}$</p><p>Soit en pourcentage : $8,10 \\times 10^{-4} \\times 100 = 0,081\\%$</p><p>L'incertitude relative est d'environ $8,10 \\times 10^{-4}$ ou 0,081%.</p>",
        "sousQuestions": []
      },
      {
        "numero": 3,
        "texte": "Présenter le résultat de la mesure sous la forme $L = L_{mes} \\pm \\Delta L$.",
        "niveau": "easy",
        "reponse": "<p>Le résultat s'écrit : $L = 1,234 \\pm 0,001 \\ m$</p><p>Cela signifie que la longueur réelle de la table est comprise entre 1,233 m et 1,235 m.</p>",
        "sousQuestions": []
      }
    ]
  },
  {
    "intitule": "Erreurs aléatoires et systématiques",
    "type": "ressource",
    "niveau": "medium",
    "enonce": {
      "texte": "<p>Un élève effectue plusieurs mesures de la masse d'un objet à l'aide d'une balance.</p><p>Il obtient les valeurs suivantes : 120,3 g ; 120,5 g ; 120,4 g ; 120,6 g ; 120,3 g.</p><p>La balance n'a pas été tarée correctement et indique systématiquement 0,5 g de trop.</p>",
      "images": []
    },
    "questions": [
      {
        "numero": 1,
        "texte": "Calculer la moyenne $\\bar{x}$ des mesures.",
        "niveau": "easy",
        "reponse": "<p>$\\bar{x} = \\dfrac{120,3 + 120,5 + 120,4 + 120,6 + 120,3}{5}$</p><p>$\\bar{x} = \\dfrac{602,1}{5} = 120,42\\ g$</p><p>La moyenne des mesures est de 120,42 g.</p>",
        "sousQuestions": []
      },
      {
        "numero": 2,
        "texte": "Distinguer l'erreur aléatoire et l'erreur systématique dans cet exemple.",
        "niveau": "medium",
        "reponse": "<p><strong>Erreur aléatoire :</strong> Les variations entre les mesures (120,3 ; 120,5 ; 120,4 ; 120,6 ; 120,3) sont des erreurs aléatoires. Elles sont dues aux fluctuations de la lecture ou aux conditions de mesure. Elles font varier les résultats autour d'une valeur moyenne.</p><p><strong>Erreur systématique :</strong> La balance qui indique 0,5 g de trop est une erreur systématique. Elle est constante et déplace tous les résultats dans le même sens. On peut la corriger en retranchant 0,5 g à chaque mesure.</p>",
        "sousQuestions": []
      },
      {
        "numero": 3,
        "texte": "Proposer une correction pour éliminer l'erreur systématique.",
        "niveau": "easy",
        "reponse": "<p>Pour corriger l'erreur systématique, il faut retrancher 0,5 g à chaque mesure.</p><p>La masse réelle de l'objet est donc : $m_{r\\'eelle} = \\bar{x} - 0,5 = 120,42 - 0,5 = 119,92\\ g$</p><p>Si on corrige chaque mesure individuellement : 119,8 ; 120,0 ; 119,9 ; 120,1 ; 119,8 g.</p>",
        "sousQuestions": []
      }
    ]
  },
  {
    "intitule": "Propagation des incertitudes",
    "type": "ressource",
    "niveau": "hard",
    "enonce": {
      "texte": "<p>On mesure la longueur $L$ et la largeur $l$ d'un rectangle pour calculer sa surface $S = L \\times l$.</p><p>Les mesures donnent : $L = 5,00 \\pm 0,02 \\ cm$ et $l = 3,00 \\pm 0,01 \\ cm$.</p>",
      "images": []
    },
    "questions": [
      {
        "numero": 1,
        "texte": "Calculer la surface $S$ du rectangle.",
        "niveau": "easy",
        "reponse": "<p>$S = L \\times l = 5,00 \\times 3,00 = 15,00\\ cm^2$</p><p>La surface du rectangle est de 15,00 cm².</p>",
        "sousQuestions": []
      },
      {
        "numero": 2,
        "texte": "Utiliser la règle de propagation des erreurs pour un produit pour calculer l'incertitude $\\Delta S$ sur la surface.",
        "niveau": "hard",
        "reponse": "<p>La règle de propagation pour un produit : $\\dfrac{\\Delta S}{S} = \\dfrac{\\Delta L}{L} + \\dfrac{\\Delta l}{l}$</p><p>$\\dfrac{\\Delta L}{L} = \\dfrac{0,02}{5,00} = 0,004$</p><p>$\\dfrac{\\Delta l}{l} = \\dfrac{0,01}{3,00} \\approx 0,0033$</p><p>$\\dfrac{\\Delta S}{S} = 0,004 + 0,0033 = 0,0073$</p><p>$\\Delta S = S \\times 0,0073 = 15,00 \\times 0,0073 \\approx 0,11\\ cm^2$</p><p>L'incertitude sur la surface est d'environ 0,11 cm².</p>",
        "sousQuestions": []
      },
      {
        "numero": 3,
        "texte": "Exprimer le résultat final de la surface avec son incertitude.",
        "niveau": "medium",
        "reponse": "<p>$S = 15,00 \\pm 0,11\\ cm^2$</p><p>La surface du rectangle est comprise entre 14,89 cm² et 15,11 cm².</p><p>L'incertitude relative est de 0,73%.</p>",
        "sousQuestions": []
      }
    ]
  },
  {
    "intitule": "Application à une mesure de vitesse",
    "type": "competence",
    "niveau": "medium",
    "enonce": {
      "texte": "<p>Un élève mesure la distance parcourue par une voiture jouet sur une piste et le temps mis pour parcourir cette distance.</p><p>Il obtient : $d = 2,50 \\ m$ avec une incertitude $\\Delta d = 0,05 \\ m$ et $t = 5,00 \\ s$ avec une incertitude $\\Delta t = 0,10 \\ s$.</p><p>La vitesse moyenne est donnée par $v = \\dfrac{d}{t}$.</p>",
      "images": [
        "Schéma d'une voiture jouet sur une piste avec un chronomètre pour mesurer le temps."
      ]
    },
    "questions": [
      {
        "numero": 1,
        "texte": "Calculer la vitesse moyenne de la voiture.",
        "niveau": "easy",
        "reponse": "<p>$v = \\dfrac{d}{t} = \\dfrac{2,50}{5,00} = 0,500\\ m/s$</p><p>La vitesse moyenne de la voiture est de 0,500 m/s.</p>",
        "sousQuestions": []
      },
      {
        "numero": 2,
        "texte": "Utiliser la règle de propagation des erreurs pour un rapport pour calculer l'incertitude $\\Delta v$ sur la vitesse.",
        "niveau": "hard",
        "reponse": "<p>Pour un rapport, on a : $\\dfrac{\\Delta v}{v} = \\dfrac{\\Delta d}{d} + \\dfrac{\\Delta t}{t}$</p><p>$\\dfrac{\\Delta d}{d} = \\dfrac{0,05}{2,50} = 0,020$</p><p>$\\dfrac{\\Delta t}{t} = \\dfrac{0,10}{5,00} = 0,020$</p><p>$\\dfrac{\\Delta v}{v} = 0,020 + 0,020 = 0,040$</p><p>$\\Delta v = v \\times 0,040 = 0,500 \\times 0,040 = 0,020\\ m/s$</p><p>L'incertitude sur la vitesse est de 0,020 m/s.</p>",
        "sousQuestions": []
      },
      {
        "numero": 3,
        "texte": "Exprimer le résultat final de la vitesse avec son incertitude.",
        "niveau": "medium",
        "reponse": "<p>$v = 0,500 \\pm 0,020\\ m/s$</p><p>La vitesse de la voiture est comprise entre 0,480 m/s et 0,520 m/s.</p><p>L'incertitude relative est de 4,0%.</p>",
        "sousQuestions": []
      }
    ]
  },
  {
    "intitule": "Étude d'une série de mesures",
    "type": "competence",
    "niveau": "hard",
    "enonce": {
      "texte": "<p>Un technicien mesure la résistance électrique d'un conducteur ohmique à l'aide d'un ohmmètre.</p><p>Il effectue 6 mesures et obtient : 10,2 Ω ; 10,4 Ω ; 10,3 Ω ; 10,5 Ω ; 10,3 Ω ; 10,4 Ω.</p><p>L'ohmmètre utilisé a une précision de 0,1 Ω.</p>",
      "images": []
    },
    "questions": [
      {
        "numero": 1,
        "texte": "Calculer la moyenne $\\bar{R}$ des mesures.",
        "niveau": "easy",
        "reponse": "<p>$\\bar{R} = \\dfrac{10,2 + 10,4 + 10,3 + 10,5 + 10,3 + 10,4}{6}$</p><p>$\\bar{R} = \\dfrac{62,1}{6} = 10,35\\ \\Omega$</p><p>La moyenne des mesures est de 10,35 Ω.</p>",
        "sousQuestions": []
      },
      {
        "numero": 2,
        "texte": "Déterminer l'incertitude absolue due à l'instrument ($\\Delta R_{inst}$) et l'incertitude due à la dispersion des mesures ($\\Delta R_{disp}$). On prendra pour la dispersion l'écart maximal : $\\Delta R_{disp} = \\dfrac{R_{max} - R_{min}}{2}$.",
        "niveau": "hard",
        "reponse": "<p><strong>Incertitude instrumentale :</strong> $\\Delta R_{inst} = 0,1\\ \\Omega$ (précision de l'ohmmètre).</p><p><strong>Incertitude de dispersion :</strong></p><p>$R_{max} = 10,5\\ \\Omega$ et $R_{min} = 10,2\\ \\Omega$</p><p>$\\Delta R_{disp} = \\dfrac{10,5 - 10,2}{2} = \\dfrac{0,3}{2} = 0,15\\ \\Omega$</p><p>L'incertitude due à la dispersion est de 0,15 Ω.</p>",
        "sousQuestions": []
      },
      {
        "numero": 3,
        "texte": "Calculer l'incertitude absolue totale $\\Delta R$ en additionnant les deux incertitudes (méthode pessimiste).",
        "niveau": "medium",
        "reponse": "<p>$\\Delta R = \\Delta R_{inst} + \\Delta R_{disp} = 0,1 + 0,15 = 0,25\\ \\Omega$</p><p>L'incertitude absolue totale est de 0,25 Ω.</p>",
        "sousQuestions": []
      },
      {
        "numero": 4,
        "texte": "Exprimer le résultat final de la mesure avec son incertitude.",
        "niveau": "medium",
        "reponse": "<p>$R = 10,35 \\pm 0,25\\ \\Omega$</p><p>La résistance réelle est comprise entre 10,10 Ω et 10,60 Ω.</p><p>L'incertitude relative est : $\\dfrac{0,25}{10,35} \\approx 0,024 = 2,4\\%$</p>",
        "sousQuestions": []
      }
    ]
  },
  {
    "intitule": "Propagation d'incertitude pour une loi puissance",
    "type": "ressource",
    "niveau": "very hard",
    "enonce": {
      "texte": "<p>Pour calculer l'énergie cinétique d'un mobile, on utilise la formule $E_c = \\dfrac{1}{2} m v^2$.</p><p>Les mesures donnent : $m = 2,00 \\pm 0,01\\ kg$ et $v = 3,00 \\pm 0,05\\ m/s$.</p>",
      "images": []
    },
    "questions": [
      {
        "numero": 1,
        "texte": "Calculer l'énergie cinétique $E_c$.",
        "niveau": "easy",
        "reponse": "<p>$E_c = \\dfrac{1}{2} \\times 2,00 \\times (3,00)^2 = 1,00 \\times 9,00 = 9,00\\ J$</p><p>L'énergie cinétique est de 9,00 J.</p>",
        "sousQuestions": []
      },
      {
        "numero": 2,
        "texte": "Utiliser la règle de propagation pour une loi puissance pour calculer l'incertitude relative $\\dfrac{\\Delta E_c}{E_c}$.",
        "niveau": "very hard",
        "reponse": "<p>Pour une loi puissance $G = k \\times x^n$, on a $\\dfrac{\\Delta G}{G} = |n| \\times \\dfrac{\\Delta x}{x}$.</p><p>Ici, $E_c = \\dfrac{1}{2} m v^2$.</p><p>$\\dfrac{\\Delta E_c}{E_c} = \\dfrac{\\Delta m}{m} + 2 \\times \\dfrac{\\Delta v}{v}$</p><p>$\\dfrac{\\Delta m}{m} = \\dfrac{0,01}{2,00} = 0,005$</p><p>$\\dfrac{\\Delta v}{v} = \\dfrac{0,05}{3,00} \\approx 0,0167$</p><p>$\\dfrac{\\Delta E_c}{E_c} = 0,005 + 2 \\times 0,0167 = 0,005 + 0,0333 = 0,0383$</p><p>L'incertitude relative est de 0,0383, soit environ 3,83%.</p>",
        "sousQuestions": []
      },
      {
        "numero": 3,
        "texte": "Calculer l'incertitude absolue $\\Delta E_c$.",
        "niveau": "medium",
        "reponse": "<p>$\\Delta E_c = E_c \\times \\dfrac{\\Delta E_c}{E_c} = 9,00 \\times 0,0383 \\approx 0,345\\ J$</p><p>L'incertitude absolue est d'environ 0,345 J.</p>",
        "sousQuestions": []
      },
      {
        "numero": 4,
        "texte": "Exprimer le résultat final de l'énergie cinétique avec son incertitude.",
        "niveau": "medium",
        "reponse": "<p>$E_c = 9,00 \\pm 0,345\\ J$</p><p>Soit avec un nombre raisonnable de chiffres significatifs : $E_c = 9,0 \\pm 0,3\\ J$</p><p>L'énergie cinétique est comprise entre 8,7 J et 9,3 J.</p>",
        "sousQuestions": []
      }
    ]
  }
]