[
  {
    "questionText": "Which question is used to ask someone's name?",
    "options": [
      "How old are you?",
      "What's your name?",
      "Where are you from?",
      "What class are you in?"
    ],
    "correctAnswer": 1,
    "difficulty": "easy",
    "explanation": "The question 'What's your name?' is specifically used to ask for someone's name. 'How old are you?' asks about age, 'Where are you from?' asks about place of origin, and 'What class are you in?' asks about class."
  },
  {
    "questionText": "How do you ask someone about their age?",
    "options": [
      "What is your name?",
      "How old are you?",
      "Where do you live?",
      "What class are you in?"
    ],
    "correctAnswer": 1,
    "difficulty": "easy",
    "explanation": "'How old are you?' is the correct question to ask about someone's age. 'What is your name?' asks for name, 'Where do you live?' asks for location, and 'What class are you in?' asks for class information."
  },
  {
    "questionText": "Choose the correct form of the verb 'to be': She _______ a student.",
    "options": [
      "am",
      "is",
      "are",
      "be"
    ],
    "correctAnswer": 1,
    "difficulty": "easy",
    "explanation": "The correct form of the verb 'to be' for the third person singular (She, He, It) is 'is'. 'Am' is used with 'I', 'are' is used with 'You, We, They', and 'be' is the base form."
  },
  {
    "questionText": "Choose the correct form of the verb 'to have': I _______ a brother.",
    "options": [
      "has",
      "have",
      "am",
      "is"
    ],
    "correctAnswer": 1,
    "difficulty": "easy",
    "explanation": "The correct form of the verb 'to have' for the first person singular (I) is 'have'. 'Has' is used with third person singular (He, She, It). 'Am' and 'is' are forms of the verb 'to be'."
  },
  {
    "questionText": "What is the negative form of 'I have a sister.'?",
    "options": [
      "I not have a sister.",
      "I don't have a sister.",
      "I hasn't a sister.",
      "I am not have a sister."
    ],
    "correctAnswer": 1,
    "difficulty": "medium",
    "explanation": "The negative form of 'I have' is 'I don't have'. The other options are grammatically incorrect. We use the auxiliary verb 'do' to form the negative in the present simple tense with 'have'."
  },
  {
    "questionText": "Which question is correct to ask about someone's class?",
    "options": [
      "What are you class?",
      "What class are you in?",
      "What class is you?",
      "What are you in class?"
    ],
    "correctAnswer": 1,
    "difficulty": "medium",
    "explanation": "The correct question to ask about someone's class is 'What class are you in?' The other options have incorrect word order or missing prepositions."
  },
  {
    "questionText": "Complete the sentence: They _______ 10 years old.",
    "options": [
      "am",
      "is",
      "are",
      "have"
    ],
    "correctAnswer": 2,
    "difficulty": "medium",
    "explanation": "The correct form of the verb 'to be' for the third person plural (They) is 'are'. 'Am' is used with 'I', 'is' with singular nouns, and 'have' is the verb 'to have'."
  },
  {
    "questionText": "Complete the sentence: She _______ a dog.",
    "options": [
      "has",
      "have",
      "am",
      "is"
    ],
    "correctAnswer": 0,
    "difficulty": "medium",
    "explanation": "The correct form of the verb 'to have' for the third person singular (She, He, It) is 'has'. 'Have' is used with 'I, You, We, They'. 'Am' and 'is' are forms of the verb 'to be'."
  },
  {
    "questionText": "Which sentence is correct?",
    "options": [
      "I am 10 old years.",
      "I have 10 years old.",
      "I am 10 years old.",
      "I is 10 years old."
    ],
    "correctAnswer": 2,
    "difficulty": "medium",
    "explanation": "The correct way to state age is 'I am 10 years old.' The verb 'to be' is used with age, and the order of words is 'subject + am/is/are + number + years old'."
  },
  {
    "questionText": "What is the correct interrogative form of 'He has a book.'?",
    "options": [
      "Has he a book?",
      "Does he have a book?",
      "Have he a book?",
      "Is he have a book?"
    ],
    "correctAnswer": 1,
    "difficulty": "hard",
    "explanation": "The correct interrogative form is 'Does he have a book?' In questions with the verb 'to have' (when it means possession), we use the auxiliary verb 'do/does' in the present simple tense. 'Has he a book?' is grammatically incorrect in modern English."
  },
  {
    "questionText": "Choose the correct question for this answer: 'My name is John.'",
    "options": [
      "How old are you?",
      "What class are you in?",
      "What's your name?",
      "Where do you live?"
    ],
    "correctAnswer": 2,
    "difficulty": "hard",
    "explanation": "The question that matches the answer 'My name is John' is 'What's your name?' The other questions would have different answers: 'How old are you?' (age), 'What class are you in?' (class), and 'Where do you live?' (location)."
  },
  {
    "questionText": "Complete the negative sentence: She _______ a cat.",
    "options": [
      "not have",
      "doesn't have",
      "doesn't has",
      "don't have"
    ],
    "correctAnswer": 1,
    "difficulty": "hard",
    "explanation": "The correct negative form is 'She doesn't have a cat.' For third person singular, we use 'doesn't' + base form of the verb (have). 'Doesn't has' is incorrect because we use the base form after 'doesn't'."
  },
  {
    "questionText": "Which sentence correctly gives personal information?",
    "options": [
      "My name is Mary, and I am 11 years old.",
      "My name Mary, and I am 11 years old.",
      "My name is Mary, and I have 11 years old.",
      "My name is Mary, and I is 11 years old."
    ],
    "correctAnswer": 0,
    "difficulty": "hard",
    "explanation": "The correct sentence is 'My name is Mary, and I am 11 years old.' The verb 'to be' is used with age, not 'have'. The other options have missing verbs or incorrect verb forms."
  },
  {
    "questionText": "What is the correct way to ask if someone has a pet?",
    "options": [
      "Have you a pet?",
      "Do you have a pet?",
      "Does you have a pet?",
      "Is you have a pet?"
    ],
    "correctAnswer": 1,
    "difficulty": "hard",
    "explanation": "The correct question is 'Do you have a pet?' In questions with the verb 'to have' (when it means possession), we use the auxiliary verb 'do/does' in the present simple tense. 'Have you a pet?' is grammatically incorrect in modern English."
  },
  {
    "questionText": "Complete the sentence with the correct number: I am _______ years old.",
    "options": [
      "20",
      "12",
      "30",
      "45"
    ],
    "correctAnswer": 1,
    "difficulty": "very hard",
    "explanation": "The correct answer is '12' because it is a common age for a student in Class Six. The other options are also possible, but '12' is the most likely age for a student in this class."
  },
  {
    "questionText": "Which question is used to ask about someone's class?",
    "options": [
      "What is your class?",
      "What class are you in?",
      "What class is you in?",
      "What are you class?"
    ],
    "correctAnswer": 1,
    "difficulty": "very hard",
    "explanation": "The correct question is 'What class are you in?' This follows the correct word order for a question in English. The other options have incorrect word order or are ungrammatical."
  },
  {
    "questionText": "Choose the correct sentence about age in the past:",
    "options": [
      "I am 10 years old last year.",
      "I was 10 years old last year.",
      "I were 10 years old last year.",
      "I have 10 years old last year."
    ],
    "correctAnswer": 1,
    "difficulty": "very hard",
    "explanation": "The correct sentence is 'I was 10 years old last year.' The verb 'to be' in the past tense for 'I' is 'was'. 'Were' is used with 'we, you, they'. The verb 'to have' is not used with age."
  },
  {
    "questionText": "What is the correct way to ask about nationality?",
    "options": [
      "Where are you from?",
      "What is your nationality?",
      "What nationality are you?",
      "All of the above"
    ],
    "correctAnswer": 3,
    "difficulty": "very hard",
    "explanation": "All of the options are correct ways to ask about someone's nationality. 'Where are you from?' asks about place of origin, 'What is your nationality?' directly asks for nationality, and 'What nationality are you?' is also a correct question."
  },
  {
    "questionText": "Complete the question: '_______ have a sister?'",
    "options": [
      "Does you",
      "Do you",
      "Are you",
      "Is you"
    ],
    "correctAnswer": 1,
    "difficulty": "very hard",
    "explanation": "The correct question is 'Do you have a sister?' We use the auxiliary verb 'do' with the subject 'you' in questions with the verb 'to have'. 'Does' is used with 'he, she, it'. 'Are' and 'is' are forms of the verb 'to be'."
  },
  {
    "questionText": "Which sentence correctly uses the verb 'to have' in the negative?",
    "options": [
      "She don't have a brother.",
      "She doesn't have a brother.",
      "She not have a brother.",
      "She have not a brother."
    ],
    "correctAnswer": 1,
    "difficulty": "very hard",
    "explanation": "The correct negative sentence is 'She doesn't have a brother.' For third person singular, we use 'doesn't' + base form of the verb. 'Don't' is used with 'I, you, we, they'. The other options are grammatically incorrect."
  }
]