[
	{
		"id": "1",
		"nom": "La contraction de texte - principes généraux (résumé)",
		"youtubeUrl": "https://www.youtube.com/watch?v=7M1TQ5JfK9E"
	},
	{
		"id": "2",
		"nom": "Comprendre la contraction de texte en 10 minutes",
		"youtubeUrl": "https://www.youtube.com/watch?v=RY3nX7qLpNc"
	},
	{
		"id": "3",
		"nom": "Les règles essentielles du résumé de texte - Méthodologie",
		"youtubeUrl": "https://www.youtube.com/watch?v=uT2VJ_cP2Vg"
	},
	{
		"id": "4",
		"nom": "Contraction de texte : fidélité, concision et objectivité",
		"youtubeUrl": "https://www.youtube.com/watch?v=HkQ8MzDcG4I"
	},
	{
		"id": "5",
		"nom": "Réussir son résumé de texte - Les principes fondamentaux",
		"youtubeUrl": "https://www.youtube.com/watch?v=Wf0Lp9sJ3kY"
	}
]