[
    {
        "id": "1",
        "nom": "C'est quoi une machine simple ? (Physique) - Mr la science",
        "youtubeUrl": "https://www.youtube.com/watch?v=BK66ZqNlF9c"
    },
    {
        "id": "2",
        "nom": "Machines simples : plan incliné, poulie, levier (Exercices) - Prof Moustapha",
        "youtubeUrl": "https://www.youtube.com/watch?v=GtH_CXfgFi0"
    },
    {
        "id": "3",
        "nom": "Avantage mécanique d'une machine simple (C'est quoi ?)",
        "youtubeUrl": "https://www.youtube.com/watch?v=pfP4wP-F3Nw"
    }
]