[
  {
    "intitule": "Exercice 1 : Décomposition en produit de facteurs premiers",
    "type": "ressource",
    "niveau": "easy",
    "enonce": {
      "texte": "<p>Décompose les nombres suivants en produit de facteurs premiers :</p><ul><li>$144$</li><li>$225$</li><li>$360$</li><li>$2023$</li></ul>",
      "images": []
    },
    "questions": [
      {
        "numero": 1,
        "texte": "Décomposer en produit de facteurs premiers :",
        "niveau": "easy",
        "reponse": "Voir explication",
        "sousQuestions": [
          {
            "numero": "1.a",
            "texte": "$144$",
            "niveau": "easy",
            "reponse": "$144 = 2^4 \\times 3^2$"
          },
          {
            "numero": "1.b",
            "texte": "$225$",
            "niveau": "easy",
            "reponse": "$225 = 3^2 \\times 5^2$"
          },
          {
            "numero": "1.c",
            "texte": "$360$",
            "niveau": "easy",
            "reponse": "$360 = 2^3 \\times 3^2 \\times 5$"
          },
          {
            "numero": "1.d",
            "texte": "$2023$",
            "niveau": "medium",
            "reponse": "$2023 = 7 \\times 17^2$ car $2023 = 7 \\times 289 = 7 \\times 17^2$"
          }
        ]
      }
    ]
  },
  {
    "intitule": "Exercice 2 : Calcul du PGCD et du PPCM",
    "type": "ressource",
    "niveau": "medium",
    "enonce": {
      "texte": "<p>Soient $a = 588$ et $b = 840$.</p><ol><li>Déterminer $\\mathrm{PGCD}(a, b)$ en utilisant l'algorithme d'Euclide.</li><li>Déterminer $\\mathrm{PPCM}(a, b)$ à l'aide des décompositions en facteurs premiers.</li><li>Vérifier la relation $\\mathrm{PGCD}(a, b) \\times \\mathrm{PPCM}(a, b) = |a \\times b|$.</li></ol>",
      "images": []
    },
    "questions": [
      {
        "numero": 1,
        "texte": "Calculer le PGCD et le PPCM des entiers donnés.",
        "niveau": "medium",
        "reponse": "Voir explication",
        "sousQuestions": [
          {
            "numero": "1.a",
            "texte": "Déterminer $\\mathrm{PGCD}(588, 840)$ par l'algorithme d'Euclide.",
            "niveau": "medium",
            "reponse": "$\\mathrm{PGCD}(588, 840) = 84$. <br/> Étapes : <br/> $840 = 588 \\times 1 + 252$ <br/> $588 = 252 \\times 2 + 84$ <br/> $252 = 84 \\times 3 + 0$ <br/> Donc PGCD = 84."
          },
          {
            "numero": "1.b",
            "texte": "Déterminer $\\mathrm{PPCM}(588, 840)$ à l'aide des décompositions en facteurs premiers.",
            "niveau": "medium",
            "reponse": "$\\mathrm{PPCM}(588, 840) = 5880$. <br/> Décompositions : <br/> $588 = 2^2 \\times 3 \\times 7^2$ <br/> $840 = 2^3 \\times 3 \\times 5 \\times 7$ <br/> $\\mathrm{PPCM} = 2^3 \\times 3 \\times 5 \\times 7^2 = 8 \\times 3 \\times 5 \\times 49 = 5880$."
          },
          {
            "numero": "1.c",
            "texte": "Vérifier la relation $\\mathrm{PGCD}(a, b) \\times \\mathrm{PPCM}(a, b) = |a \\times b|$.",
            "niveau": "medium",
            "reponse": "$84 \\times 5880 = 493920$ et $588 \\times 840 = 493920$. La relation est vérifiée."
          }
        ]
      }
    ]
  },
  {
    "intitule": "Exercice 3 : Problème de périodicité",
    "type": "competence",
    "niveau": "medium",
    "enonce": {
      "texte": "<p>Deux train A et B partent d'une même gare. Le train A effectue son trajet en 24 minutes, tandis que le train B le fait en 36 minutes. Ils partent ensemble à 6h00.</p><ol><li>Déterminer le PGCD et le PPCM de 24 et 36.</li><li>À quel moment les deux trains se retrouveront-ils à nouveau ensemble à la gare de départ ?</li><li>Combien de fois se croiseront-ils dans la gare entre 6h00 et 12h00 ?</li></ol>",
      "images": []
    },
    "questions": [
      {
        "numero": 1,
        "texte": "Résoudre le problème de périodicité.",
        "niveau": "medium",
        "reponse": "Voir explication",
        "sousQuestions": [
          {
            "numero": "1.a",
            "texte": "Déterminer le PGCD et le PPCM de 24 et 36.",
            "niveau": "easy",
            "reponse": "$\\mathrm{PGCD}(24, 36) = 12$ et $\\mathrm{PPCM}(24, 36) = 72$."
          },
          {
            "numero": "1.b",
            "texte": "À quel moment les deux trains se retrouveront-ils à nouveau ensemble à la gare de départ ?",
            "niveau": "medium",
            "reponse": "Les trains se retrouveront toutes les 72 minutes (le PPCM). Ils se retrouveront à 6h00 + 72 min = 7h12, puis à 8h24, 9h36, 10h48, etc."
          },
          {
            "numero": "1.c",
            "texte": "Combien de fois se croiseront-ils dans la gare entre 6h00 et 12h00 ?",
            "niveau": "medium",
            "reponse": "De 6h00 à 12h00, il y a 6 heures = 360 minutes. Les trains se croisent aux multiples de 72 : 0, 72, 144, 216, 288, 360. Cela fait 6 fois (y compris le départ et l'arrivée à 12h00)."
          }
        ]
      }
    ]
  },
  {
    "intitule": "Exercice 4 : Problème de découpage",
    "type": "competence",
    "niveau": "hard",
    "enonce": {
      "texte": "<p>Une entreprise veut découper une plaque rectangulaire de dimensions $2,10$ m par $1,80$ m en carrés identiques les plus grands possibles, sans perte de matière.</p><ol><li>Déterminer la taille maximale (en cm) du côté d'un carré.</li><li>Combien de carrés pourra-t-on obtenir ?</li><li>Exprimer les dimensions en centimètres puis utiliser le PGCD.</li></ol>",
      "images": []
    },
    "questions": [
      {
        "numero": 1,
        "texte": "Résoudre le problème de découpage.",
        "niveau": "hard",
        "reponse": "Voir explication",
        "sousQuestions": [
          {
            "numero": "1.a",
            "texte": "Exprimer les dimensions en centimètres.",
            "niveau": "easy",
            "reponse": "2,10 m = 210 cm et 1,80 m = 180 cm."
          },
          {
            "numero": "1.b",
            "texte": "Déterminer la taille maximale du côté d'un carré.",
            "niveau": "hard",
            "reponse": "Le côté maximal est le PGCD de 210 et 180. <br/> $210 = 2 \\times 3 \\times 5 \\times 7$ <br/> $180 = 2^2 \\times 3^2 \\times 5$ <br/> $\\mathrm{PGCD}(210, 180) = 2 \\times 3 \\times 5 = 30$. <br/> La taille maximale est 30 cm."
          },
          {
            "numero": "1.c",
            "texte": "Combien de carrés pourra-t-on obtenir ?",
            "niveau": "medium",
            "reponse": "Nombre de carrés = $\\frac{210}{30} \\times \\frac{180}{30} = 7 \\times 6 = 42$ carrés."
          }
        ]
      }
    ]
  },
  {
    "intitule": "Exercice 5 : Nombres premiers, PGCD et PPCM",
    "type": "ressource",
    "niveau": "hard",
    "enonce": {
      "texte": "<p>Soient $n$ un entier naturel et $A = 12n + 5$, $B = 9n + 4$.</p><ol><li>Démontrer que tout diviseur commun à $A$ et $B$ divise $1$.</li><li>En déduire que $\\mathrm{PGCD}(A, B) = 1$.</li><li>Déterminer $\\mathrm{PPCM}(A, B)$ en fonction de $n$.</li></ol>",
      "images": []
    },
    "questions": [
      {
        "numero": 1,
        "texte": "Étudier les propriétés de PGCD et PPCM pour des expressions littérales.",
        "niveau": "hard",
        "reponse": "Voir explication",
        "sousQuestions": [
          {
            "numero": "1.a",
            "texte": "Démontrer que tout diviseur commun à $A$ et $B$ divise $1$.",
            "niveau": "hard",
            "reponse": "Soit $d$ un diviseur commun de $A$ et $B$. Alors $d$ divise $3A - 4B = 3(12n+5) - 4(9n+4) = 36n+15 - 36n - 16 = -1$. Donc $d$ divise $1$."
          },
          {
            "numero": "1.b",
            "texte": "En déduire que $\\mathrm{PGCD}(A, B) = 1$.",
            "niveau": "hard",
            "reponse": "Comme $d=1$, le seul diviseur commun positif est 1. Donc $\\mathrm{PGCD}(A, B) = 1$."
          },
          {
            "numero": "1.c",
            "texte": "Déterminer $\\mathrm{PPCM}(A, B)$ en fonction de $n$.",
            "niveau": "hard",
            "reponse": "$\\mathrm{PPCM}(A, B) = \\frac{|A \\times B|}{\\mathrm{PGCD}(A, B)} = (12n+5)(9n+4)$ car $\\mathrm{PGCD}=1$."
          }
        ]
      }
    ]
  },
  {
    "intitule": "Exercice 6 : Problème d'engrenage",
    "type": "competence",
    "niveau": "hard",
    "enonce": {
      "texte": "<p>Un engrenage est composé de deux roues dentées. La première roue a 24 dents et la seconde en a 36. Les deux roues sont en contact. La petite roue tourne à une vitesse de 150 tours par minute.</p><ol><li>Déterminer le PGCD et le PPCM de 24 et 36.</li><li>Combien de tours fait la grande roue quand la petite en fait 150 ?</li><li>Combien de tours fait la petite roue quand la grande en fait 100 ?</li><li>Quel est le nombre minimal de tours que doit faire la petite roue pour que les deux roues retrouvent leur position initiale ?</li></ol>",
      "images": []
    },
    "questions": [
      {
        "numero": 1,
        "texte": "Résoudre le problème d'engrenage.",
        "niveau": "hard",
        "reponse": "Voir explication",
        "sousQuestions": [
          {
            "numero": "1.a",
            "texte": "Déterminer le PGCD et le PPCM de 24 et 36.",
            "niveau": "easy",
            "reponse": "$\\mathrm{PGCD}(24, 36) = 12$ et $\\mathrm{PPCM}(24, 36) = 72$."
          },
          {
            "numero": "1.b",
            "texte": "Combien de tours fait la grande roue quand la petite en fait 150 ?",
            "niveau": "medium",
            "reponse": "Le nombre de dents étant inversement proportionnel, la grande roue fait $150 \\times \\frac{24}{36} = 150 \\times \\frac{2}{3} = 100$ tours."
          },
          {
            "numero": "1.c",
            "texte": "Combien de tours fait la petite roue quand la grande en fait 100 ?",
            "niveau": "medium",
            "reponse": "La petite roue fait $100 \\times \\frac{36}{24} = 100 \\times \\frac{3}{2} = 150$ tours."
          },
          {
            "numero": "1.d",
            "texte": "Quel est le nombre minimal de tours que doit faire la petite roue pour que les deux roues retrouvent leur position initiale ?",
            "niveau": "hard",
            "reponse": "Les roues retrouvent leur position initiale quand le nombre de tours de la petite est un multiple de 36 (pour que ses dents reviennent à la position initiale) et que la grande en fait un nombre entier de tours. Le PPCM de 24 et 36 est 72. La petite roue doit faire $72/24 = 3$ tours. La grande en fera $72/36 = 2$ tours."
          }
        ]
      }
    ]
  }
]