[
  {
    "intitule": "Exercice 1 : Addition de fractions de même dénominateur",
    "type": "ressource",
    "niveau": "easy",
    "enonce": {
      "texte": "<p>Calculer les sommes suivantes et donner le résultat sous forme de fraction simplifiée :</p>",
      "images": []
    },
    "questions": [
      {
        "numero": 1,
        "texte": "Calculer <span class='math-inline'>\\( \\frac{3}{7} + \\frac{2}{7} \\)</span>.",
        "niveau": "easy",
        "reponse": "<span class='math-inline'>\\( \\frac{3}{7} + \\frac{2}{7} = \\frac{3+2}{7} = \\frac{5}{7} \\)</span>",
        "sousQuestions": [
          {
            "numero": "1.a",
            "texte": "Calculer <span class='math-inline'>\\( \\frac{5}{9} + \\frac{8}{9} \\)</span>.",
            "niveau": "easy",
            "reponse": "<span class='math-inline'>\\( \\frac{5}{9} + \\frac{8}{9} = \\frac{5+8}{9} = \\frac{13}{9} \\)</span>"
          },
          {
            "numero": "1.b",
            "texte": "Calculer <span class='math-inline'>\\( \\frac{7}{12} + \\frac{5}{12} \\)</span>.",
            "niveau": "easy",
            "reponse": "<span class='math-inline'>\\( \\frac{7}{12} + \\frac{5}{12} = \\frac{7+5}{12} = \\frac{12}{12} = 1 \\)</span>"
          }
        ]
      }
    ]
  },
  {
    "intitule": "Exercice 2 : Soustraction de fractions de même dénominateur",
    "type": "ressource",
    "niveau": "easy",
    "enonce": {
      "texte": "<p>Effectuer les soustractions suivantes :</p>",
      "images": []
    },
    "questions": [
      {
        "numero": 1,
        "texte": "Calculer <span class='math-inline'>\\( \\frac{8}{5} - \\frac{3}{5} \\)</span>.",
        "niveau": "easy",
        "reponse": "<span class='math-inline'>\\( \\frac{8}{5} - \\frac{3}{5} = \\frac{8-3}{5} = \\frac{5}{5} = 1 \\)</span>",
        "sousQuestions": [
          {
            "numero": "1.a",
            "texte": "Calculer <span class='math-inline'>\\( \\frac{11}{4} - \\frac{7}{4} \\)</span>.",
            "niveau": "easy",
            "reponse": "<span class='math-inline'>\\( \\frac{11}{4} - \\frac{7}{4} = \\frac{11-7}{4} = \\frac{4}{4} = 1 \\)</span>"
          },
          {
            "numero": "1.b",
            "texte": "Calculer <span class='math-inline'>\\( \\frac{15}{8} - \\frac{9}{8} \\)</span>.",
            "niveau": "easy",
            "reponse": "<span class='math-inline'>\\( \\frac{15}{8} - \\frac{9}{8} = \\frac{15-9}{8} = \\frac{6}{8} = \\frac{3}{4} \\)</span> (en simplifiant par 2)"
          }
        ]
      }
    ]
  },
  {
    "intitule": "Exercice 3 : Addition de fractions de dénominateurs différents",
    "type": "ressource",
    "niveau": "medium",
    "enonce": {
      "texte": "<p>Calculer en mettant les fractions au même dénominateur :</p>",
      "images": []
    },
    "questions": [
      {
        "numero": 1,
        "texte": "Calculer <span class='math-inline'>\\( \\frac{1}{2} + \\frac{1}{3} \\)</span>.",
        "niveau": "medium",
        "reponse": "Le PPCM de 2 et 3 est 6. <span class='math-inline'>\\( \\frac{1}{2} = \\frac{3}{6} \\)</span> et <span class='math-inline'>\\( \\frac{1}{3} = \\frac{2}{6} \\)</span>.<br><span class='math-inline'>\\( \\frac{3}{6} + \\frac{2}{6} = \\frac{5}{6} \\)</span>",
        "sousQuestions": [
          {
            "numero": "1.a",
            "texte": "Calculer <span class='math-inline'>\\( \\frac{2}{3} + \\frac{5}{6} \\)</span>.",
            "niveau": "medium",
            "reponse": "Le PPCM de 3 et 6 est 6. <span class='math-inline'>\\( \\frac{2}{3} = \\frac{4}{6} \\)</span>.<br><span class='math-inline'>\\( \\frac{4}{6} + \\frac{5}{6} = \\frac{9}{6} = \\frac{3}{2} \\)</span> (en simplifiant par 3)"
          },
          {
            "numero": "1.b",
            "texte": "Calculer <span class='math-inline'>\\( \\frac{3}{4} + \\frac{5}{8} \\)</span>.",
            "niveau": "medium",
            "reponse": "Le PPCM de 4 et 8 est 8. <span class='math-inline'>\\( \\frac{3}{4} = \\frac{6}{8} \\)</span>.<br><span class='math-inline'>\\( \\frac{6}{8} + \\frac{5}{8} = \\frac{11}{8} \\)</span>"
          }
        ]
      }
    ]
  },
  {
    "intitule": "Exercice 4 : Soustraction de fractions de dénominateurs différents",
    "type": "ressource",
    "niveau": "medium",
    "enonce": {
      "texte": "<p>Calculer en mettant les fractions au même dénominateur :</p>",
      "images": []
    },
    "questions": [
      {
        "numero": 1,
        "texte": "Calculer <span class='math-inline'>\\( \\frac{5}{6} - \\frac{1}{4} \\)</span>.",
        "niveau": "medium",
        "reponse": "Le PPCM de 6 et 4 est 12. <span class='math-inline'>\\( \\frac{5}{6} = \\frac{10}{12} \\)</span> et <span class='math-inline'>\\( \\frac{1}{4} = \\frac{3}{12} \\)</span>.<br><span class='math-inline'>\\( \\frac{10}{12} - \\frac{3}{12} = \\frac{7}{12} \\)</span>",
        "sousQuestions": [
          {
            "numero": "1.a",
            "texte": "Calculer <span class='math-inline'>\\( \\frac{7}{10} - \\frac{2}{5} \\)</span>.",
            "niveau": "medium",
            "reponse": "Le PPCM de 10 et 5 est 10. <span class='math-inline'>\\( \\frac{2}{5} = \\frac{4}{10} \\)</span>.<br><span class='math-inline'>\\( \\frac{7}{10} - \\frac{4}{10} = \\frac{3}{10} \\)</span>"
          },
          {
            "numero": "1.b",
            "texte": "Calculer <span class='math-inline'>\\( \\frac{5}{3} - \\frac{1}{2} \\)</span>.",
            "niveau": "medium",
            "reponse": "Le PPCM de 3 et 2 est 6. <span class='math-inline'>\\( \\frac{5}{3} = \\frac{10}{6} \\)</span> et <span class='math-inline'>\\( \\frac{1}{2} = \\frac{3}{6} \\)</span>.<br><span class='math-inline'>\\( \\frac{10}{6} - \\frac{3}{6} = \\frac{7}{6} \\)</span>"
          }
        ]
      }
    ]
  },
  {
    "intitule": "Exercice 5 : Problème concret sur les fractions (partage de gâteau)",
    "type": "competence",
    "niveau": "hard",
    "enonce": {
      "texte": "<p>Marie a mangé <span class='math-inline'>\\( \\frac{1}{4} \\)</span> d'un gâteau, Paul en a mangé <span class='math-inline'>\\( \\frac{1}{3} \\)</span> et Julie en a mangé <span class='math-inline'>\\( \\frac{1}{6} \\)</span>.</p>",
      "images": []
    },
    "questions": [
      {
        "numero": 1,
        "texte": "Déterminer la fraction du gâteau mangée par Marie et Paul ensemble.",
        "niveau": "medium",
        "reponse": "Marie et Paul ont mangé <span class='math-inline'>\\( \\frac{1}{4} + \\frac{1}{3} \\)</span>.<br>PPCM de 4 et 3 est 12. <span class='math-inline'>\\( \\frac{1}{4} = \\frac{3}{12} \\)</span> et <span class='math-inline'>\\( \\frac{1}{3} = \\frac{4}{12} \\)</span>.<br><span class='math-inline'>\\( \\frac{3}{12} + \\frac{4}{12} = \\frac{7}{12} \\)</span>.<br>Ils ont mangé <strong><span class='math-inline'>\\( \\frac{7}{12} \\)</span></strong> du gâteau ensemble.",
        "sousQuestions": [
          {
            "numero": "1.a",
            "texte": "Quelle fraction du gâteau a été mangée par les trois personnes ?",
            "niveau": "hard",
            "reponse": "Total mangé : <span class='math-inline'>\\( \\frac{1}{4} + \\frac{1}{3} + \\frac{1}{6} \\)</span>.<br>PPCM de 4, 3 et 6 est 12. <span class='math-inline'>\\( \\frac{1}{4} = \\frac{3}{12}, \\frac{1}{3} = \\frac{4}{12}, \\frac{1}{6} = \\frac{2}{12} \\)</span>.<br><span class='math-inline'>\\( \\frac{3}{12} + \\frac{4}{12} + \\frac{2}{12} = \\frac{9}{12} = \\frac{3}{4} \\)</span>.<br>Ils ont mangé <strong><span class='math-inline'>\\( \\frac{3}{4} \\)</span></strong> du gâteau."
          },
          {
            "numero": "1.b",
            "texte": "Quelle fraction du gâteau reste-t-il ?",
            "niveau": "hard",
            "reponse": "Le gâteau entier représente 1, soit <span class='math-inline'>\\( \\frac{4}{4} \\)</span>.<br>Reste : <span class='math-inline'>\\( \\frac{4}{4} - \\frac{3}{4} = \\frac{1}{4} \\)</span>.<br>Il reste <strong><span class='math-inline'>\\( \\frac{1}{4} \\)</span></strong> du gâteau."
          }
        ]
      }
    ]
  },
  {
    "intitule": "Exercice 6 : Problème concret (longueurs)",
    "type": "competence",
    "niveau": "very hard",
    "enonce": {
      "texte": "<p>Un terrain rectangulaire mesure <span class='math-inline'>\\( \\frac{3}{4} \\)</span> de kilomètre de longueur et <span class='math-inline'>\\( \\frac{5}{6} \\)</span> de kilomètre de largeur.</p>",
      "images": []
    },
    "questions": [
      {
        "numero": 1,
        "texte": "Calculer le périmètre du terrain (en fraction de kilomètre).",
        "niveau": "very hard",
        "reponse": "Périmètre = 2 × (Longueur + Largeur).<br><span class='math-inline'>\\( 2 \\times \\left( \\frac{3}{4} + \\frac{5}{6} \\right) \\)</span><br>PPCM de 4 et 6 est 12. <span class='math-inline'>\\( \\frac{3}{4} = \\frac{9}{12} \\)</span> et <span class='math-inline'>\\( \\frac{5}{6} = \\frac{10}{12} \\)</span>.<br><span class='math-inline'>\\( \\frac{9}{12} + \\frac{10}{12} = \\frac{19}{12} \\)</span>.<br><span class='math-inline'>\\( 2 \\times \\frac{19}{12} = \\frac{38}{12} = \\frac{19}{6} \\)</span> km.<br>Le périmètre est de <strong><span class='math-inline'>\\( \\frac{19}{6} \\)</span> km</strong>.",
        "sousQuestions": [
          {
            "numero": "1.a",
            "texte": "Quelle est la différence entre la longueur et la largeur ?",
            "niveau": "hard",
            "reponse": "Différence = Longueur - Largeur = <span class='math-inline'>\\( \\frac{3}{4} - \\frac{5}{6} \\)</span>.<br><span class='math-inline'>\\( \\frac{9}{12} - \\frac{10}{12} = -\\frac{1}{12} \\)</span>.<br>La longueur est plus petite que la largeur de <span class='math-inline'>\\( \\frac{1}{12} \\)</span> km (ou la largeur est plus grande que la longueur de <span class='math-inline'>\\( \\frac{1}{12} \\)</span> km)."
          }
        ]
      }
    ]
  },
  {
    "intitule": "Exercice 7 : Addition et soustraction de fractions avec nombres entiers",
    "type": "ressource",
    "niveau": "medium",
    "enonce": {
      "texte": "<p>Calculer les expressions suivantes :</p>",
      "images": []
    },
    "questions": [
      {
        "numero": 1,
        "texte": "Calculer <span class='math-inline'>\\( 2 + \\frac{1}{3} \\)</span>.",
        "niveau": "medium",
        "reponse": "<span class='math-inline'>\\( 2 = \\frac{2}{1} = \\frac{6}{3} \\)</span>.<br><span class='math-inline'>\\( \\frac{6}{3} + \\frac{1}{3} = \\frac{7}{3} \\)</span>",
        "sousQuestions": [
          {
            "numero": "1.a",
            "texte": "Calculer <span class='math-inline'>\\( 3 - \\frac{2}{5} \\)</span>.",
            "niveau": "medium",
            "reponse": "<span class='math-inline'>\\( 3 = \\frac{3}{1} = \\frac{15}{5} \\)</span>.<br><span class='math-inline'>\\( \\frac{15}{5} - \\frac{2}{5} = \\frac{13}{5} \\)</span>"
          }
        ]
      }
    ]
  }
]